calc_package/__init__.py
calc_package/calc.py
calc_package/unit_tests.py
calculate_application_eyal-0.0.1.dist-info/METADATA
calculate_application_eyal-0.0.1.dist-info/WHEEL
calculate_application_eyal-0.0.1.dist-info/top_level.txt
calculate_application_eyal-0.0.1.dist-info/RECORD
